yta_audio_narration_google/__init__.py
yta_audio_narration_google-0.0.1.dist-info/LICENSE
yta_audio_narration_google-0.0.1.dist-info/METADATA
yta_audio_narration_google-0.0.1.dist-info/WHEEL
yta_audio_narration_google-0.0.1.dist-info/RECORD
